leady/__init__.py
leady-0.1.4.dist-info/DESCRIPTION.rst
leady-0.1.4.dist-info/METADATA
leady-0.1.4.dist-info/RECORD
leady-0.1.4.dist-info/WHEEL
leady-0.1.4.dist-info/metadata.json
leady-0.1.4.dist-info/top_level.txt
tests_leady/__init__.py
tests_leady/test_leady.py
