Metadata-Version: 2.0
Name: leady
Version: 0.1.4
Summary: Leady Analytics Tracking API
Home-page: https://github.com/impercz/leady-python-sdk
Author: Vitek Pliska
Author-email: vitek@creatiweb.cz
License: LICENSE
Platform: UNKNOWN
Classifier: Development Status :: 4 - Beta
Classifier: License :: OSI Approved :: BSD License
Classifier: Operating System :: OS Independent
Classifier: Programming Language :: Python
Classifier: Programming Language :: Python :: 2
Classifier: Programming Language :: Python :: 3
Classifier: Topic :: Utilities
